ilionpy/BasicMath.py
ilionpy/Numbers.py
ilionpy/__init__.py
ilionpy/test.py
ilionpy-0.0.5.dist-info/License.txt
ilionpy-0.0.5.dist-info/METADATA
ilionpy-0.0.5.dist-info/WHEEL
ilionpy-0.0.5.dist-info/top_level.txt
ilionpy-0.0.5.dist-info/RECORD
