Metadata-Version: 2.1
Name: ilionpy
Version: 0.0.5
Summary: Ilion Function Library
Home-page: http://www.ilionanalytics.com
Author: Peter Gross
Author-email: peter@ilion.co.za
License: UNKNOWN
Platform: UNKNOWN
Classifier: Programming Language :: Python :: 3
Classifier: License :: OSI Approved :: MIT License
Classifier: Operating System :: OS Independent
Requires-Python: >=3.6
